odoo/addons/project_internal_note/README.rst
odoo/addons/project_internal_note/__init__.py
odoo/addons/project_internal_note/__manifest__.py
odoo/addons/project_internal_note/i18n/ca_ES.po
odoo/addons/project_internal_note/i18n/es.po
odoo/addons/project_internal_note/models/__init__.py
odoo/addons/project_internal_note/models/project_project.py
odoo/addons/project_internal_note/models/project_task.py
odoo/addons/project_internal_note/readme/CONTRIBUTORS.md
odoo/addons/project_internal_note/readme/DESCRIPTION.md
odoo/addons/project_internal_note/readme/USAGE.md
odoo/addons/project_internal_note/static/description/icon.png
odoo/addons/project_internal_note/static/description/index.html
odoo/addons/project_internal_note/tests/__init__.py
odoo/addons/project_internal_note/tests/test_project_internal_note.py
odoo/addons/project_internal_note/views/project_task_views.xml
odoo/addons/project_internal_note/views/project_views.xml
odoo_addon_project_internal_note-18.0.1.0.0.1.dist-info/METADATA
odoo_addon_project_internal_note-18.0.1.0.0.1.dist-info/WHEEL
odoo_addon_project_internal_note-18.0.1.0.0.1.dist-info/top_level.txt
odoo_addon_project_internal_note-18.0.1.0.0.1.dist-info/RECORD
